{
  "full_title": "Distill",
  "abbrev_title": "Distill",
  "doi": "00.0000/dstl",
  "issn": "0000-0000",
  "posts": [
      {
        "publishPath": "2016/handwriting",
        "githubRepo": "distillpub/post--handwriting",
        "doi_suffix": 4
      },
      {
        "publishPath": "2016/deconv-checkerboard",
        "githubRepo": "distillpub/post--deconv-checkerboard",
        "doi_suffix": 3
      },
      {
        "publishPath": "2016/misread-tsne",
        "githubRepo": "distillpub/post--misread-tsne",
        "doi_suffix": 2
      },
      {
        "publishPath": "2016/augmented-rnns",
        "githubRepo": "distillpub/post--augmented-rnns",
        "doi_suffix": 1
      },
      {
        "publishPath": "/faq",
        "githubRepo": "distillpub/post--faq",
        "no-homepage": "true"
      }
    ]
}
